Metadata-Version: 2.4
Name: dbt-spark
Version: 1.10.0
Summary: The Apache Spark adapter plugin for dbt
Project-URL: Homepage, https://github.com/dbt-labs/dbt-adapters/tree/main/dbt-spark
Project-URL: Documentation, https://docs.getdbt.com
Project-URL: Repository, https://github.com/dbt-labs/dbt-adapters.git#subdirectory=dbt-spark
Project-URL: Issues, https://github.com/dbt-labs/dbt-adapters/issues
Project-URL: Changelog, https://github.com/dbt-labs/dbt-adapters/blob/main/dbt-spark/CHANGELOG.md
Author-email: dbt Labs <info@dbtlabs.com>
Maintainer-email: dbt Labs <info@dbtlabs.com>
License-File: LICENSE
Keywords: adapter,adapters,database,dbt,dbt Cloud,dbt Core,dbt Labs,dbt-core,elt,spark
Classifier: Development Status :: 5 - Production/Stable
Classifier: License :: OSI Approved :: Apache Software License
Classifier: Operating System :: MacOS :: MacOS X
Classifier: Operating System :: Microsoft :: Windows
Classifier: Operating System :: POSIX :: Linux
Classifier: Programming Language :: Python :: 3.10
Classifier: Programming Language :: Python :: 3.11
Classifier: Programming Language :: Python :: 3.12
Classifier: Programming Language :: Python :: 3.13
Requires-Python: >=3.10.0
Requires-Dist: dbt-adapters<2.0,>=1.7
Requires-Dist: dbt-common<2.0,>=1.10
Requires-Dist: dbt-core>=1.8.0
Requires-Dist: sqlparams>=3.0.0
Provides-Extra: all
Requires-Dist: pyhive[hive-pure-sasl]~=0.7.0; extra == 'all'
Requires-Dist: pyodbc<5.3,>=5.1; extra == 'all'
Requires-Dist: pyspark<4.0.0,>=3.0.0; extra == 'all'
Requires-Dist: thrift<0.17.0,>=0.11.0; extra == 'all'
Provides-Extra: odbc
Requires-Dist: pyodbc<5.3,>=5.1; extra == 'odbc'
Provides-Extra: pyhive
Requires-Dist: pyhive[hive-pure-sasl]~=0.7.0; extra == 'pyhive'
Requires-Dist: thrift<0.17.0,>=0.11.0; extra == 'pyhive'
Provides-Extra: session
Requires-Dist: pyspark<4.0.0,>=3.0.0; extra == 'session'
